gooey/__init__.py
gooey/client.py
gooey/copilot/__init__.py
gooey/copilot/client.py
gooey/copilot/types/__init__.py
gooey/copilot/types/copilot_completion_request_functions_item.py
gooey/copilot/types/copilot_completion_request_sadtalker_settings.py
gooey/copilot/types/copilot_completion_request_sadtalker_settings_preprocess.py
gooey/core/__init__.py
gooey/core/api_error.py
gooey/core/client_wrapper.py
gooey/core/datetime_utils.py
gooey/core/file.py
gooey/core/http_client.py
gooey/core/jsonable_encoder.py
gooey/core/pydantic_utilities.py
gooey/core/query_encoder.py
gooey/core/remove_none_from_dict.py
gooey/core/request_options.py
gooey/core/serialization.py
gooey/environment.py
gooey/errors/__init__.py
gooey/errors/payment_required_error.py
gooey/errors/too_many_requests_error.py
gooey/errors/unprocessable_entity_error.py
gooey/py.typed
gooey/types/__init__.py
gooey/types/agg_function.py
gooey/types/agg_function_function.py
gooey/types/agg_function_result.py
gooey/types/agg_function_result_function.py
gooey/types/animation_models.py
gooey/types/animation_prompt.py
gooey/types/asr_chunk.py
gooey/types/asr_models.py
gooey/types/asr_output_format.py
gooey/types/asr_output_json.py
gooey/types/asr_page_output.py
gooey/types/asr_page_output_output_text_item.py
gooey/types/asr_page_request.py
gooey/types/asr_page_status_response.py
gooey/types/async_api_response_model_v3.py
gooey/types/balance_response.py
gooey/types/bot_broadcast_filters.py
gooey/types/bot_broadcast_request_model.py
gooey/types/bulk_eval_page_output.py
gooey/types/bulk_eval_page_status_response.py
gooey/types/bulk_runner_page_output.py
gooey/types/bulk_runner_page_request.py
gooey/types/bulk_runner_page_status_response.py
gooey/types/button_pressed.py
gooey/types/called_function_response.py
gooey/types/chat_completion_content_part_image_param.py
gooey/types/chat_completion_content_part_text_param.py
gooey/types/chyron_plant_page_output.py
gooey/types/chyron_plant_page_request.py
gooeyai-0.0.1b28.dist-info/METADATA
gooeyai-0.0.1b28.dist-info/WHEEL
gooeyai-0.0.1b28.dist-info/RECORD
